Workbook

Sheet Dealers
A1: DealerID | B1: DealerName | C1: City | D1: Country
A2: 1 | B2: ABC Motors | C2: Kuala Lumpur | D2: Malaysia
A3: 2 | B3: XYZ Cars | C3: George Town | D3: Malaysia
A4: 3 | B4: Singapore Autos | C4: Singapore | D4: Singapore
A5: 4 | B5: Manila Motors | C5: Manila | D5: Philippines
A6: 5 | B6: Cebu Cars | C6: Cebu City | D6: Philippines
A7: 6 | B7: Davao Dealers | C7: Davao City | D7: Philippines
A8: 7 | B8: Quezon Vehicles | C8: Quezon City | D8: Philippines
A9: 8 | B9: Bacolod Autos | C9: Bacolod City | D9: Philippines
A10: 9 | B10: Iloilo Motors | C10: Iloilo City | D10: Philippines
A11: 10 | B11: Zamboanga Cars | C11: Zamboanga City | D11: Philippines

Sheet Models
A1: ModelID | B1: Brand | C1: Model | D1: Segment | E1: EngineSize (L) | F1: Fuel | G1: Price (USD) | H1: Profit (USD)
A2: 1 | B2: Toyota | C2: Vios | D2: Sedan | E2: 1.5 | F2: Gasoline | G2: 15000 | H2: =Table1[[#This Row],[Price (USD)]]*0.1 -> 1500
A3: 2 | B3: Toyota | C3: Corolla Altis | D3: Sedan | E3: 1.8 | F3: Gasoline | G3: 20000 | H3: =Table1[[#This Row],[Price (USD)]]*0.1 -> 2000
A4: 3 | B4: Honda | C4: Civic | D4: Sedan | E4: 1.8 | F4: Gasoline | G4: 22000 | H4: =Table1[[#This Row],[Price (USD)]]*0.2 -> 4400
A5: 4 | B5: Honda | C5: CR-V | D5: SUV | E5: 2.4 | F5: Gasoline | G5: 28000 | H5: =Table1[[#This Row],[Price (USD)]]*0.1 -> 2800
A6: 5 | B6: Ford | C6: Ranger | D6: Pickup | E6: 2.0 | F6: Diesel | G6: 25000 | H6: =Table1[[#This Row],[Price (USD)]]*0.1 -> 2500
A7: 6 | B7: Ford | C7: Everest | D7: SUV | E7: 2.0 | F7: Diesel | G7: 30000 | H7: =Table1[[#This Row],[Price (USD)]]*0.1 -> 3000
A8: 7 | B8: Nissan | C8: Almera | D8: Sedan | E8: 1.2 | F8: Gasoline | G8: 14000 | H8: =Table1[[#This Row],[Price (USD)]]*0.1 -> 1400
A9: 8 | B9: Nissan | C9: X-Trail | D9: SUV | E9: 2.5 | F9: Gasoline | G9: 26000 | H9: =Table1[[#This Row],[Price (USD)]]*0.1 -> 2600
A10: 9 | B10: Mitsubishi | C10: Xpander | D10: MPV | E10: 1.5 | F10: Gasoline | G10: 18000 | H10: =Table1[[#This Row],[Price (USD)]]*0.1 -> 1800
A11: 10 | B11: Mitsubishi | C11: Outlander | D11: SUV | E11: 2.4 | F11: Gasoline | G11: 32000 | H11: =Table1[[#This Row],[Price (USD)]]*0.1 -> 3200
A12: 11 | B12: Hyundai | C12: Accent | D12: Sedan | E12: 1.6 | F12: Gasoline | G12: 16000 | H12: =Table1[[#This Row],[Price (USD)]]*0.2 -> 3200
A13: 12 | B13: Hyundai | C13: Santa Fe | D13: SUV | E13: 2.4 | F13: Gasoline | G13: 34000 | H13: =Table1[[#This Row],[Price (USD)]]*0.1 -> 3400
A14: 13 | B14: Proton | C14: Persona | D14: Sedan | E14: 1.6 | F14: Gasoline | G14: 12000 | H14: =Table1[[#This Row],[Price (USD)]]*0.1 -> 1200
A15: 14 | B15: Proton | C15: X70 | D15: SUV | E15: 1.8 | F15: Gasoline | G15: 25000 | H15: =Table1[[#This Row],[Price (USD)]]*0.2 -> 5000
A16: 15 | B16: Mazda | C16: Mazda3 | D16: Sedan | E16: 2.0 | F16: Gasoline | G16: 24000 | H16: =Table1[[#This Row],[Price (USD)]]*0.1 -> 2400

Sheet Sales
A1: SaleID | B1: Date | C1: DealerID | D1: ModelID | E1: Quantity | F1: TotalPrice | G1: Total Profit | H1: Country | I1: Cars | J1: Brands | K1: City | L1: Dealer
A2: 1 | B2: 44566 | C2: =RANDBETWEEN(1,10) -> 9 | D2: =RANDBETWEEN(1,15) -> 15 | E2: 1 | F2: =Table2[[#This Row],[Quantity]]*(INDEX(Models!G:G,MATCH(Table2[[#This Row],[ModelID]],Models!A:A,0))) -> 24000 | G2: =Table2[[#This Row],[Quantity]]*(INDEX(Models!H:H,MATCH(Table2[[#This Row],[ModelID]],Models!A:A,0))) -> 2400 | H2: =VLOOKUP(Table2[[#This Row],[DealerID]], Dealers!A:D, 4,FALSE) -> Philippines | I2: =VLOOKUP(Table2[[#This Row],[ModelID]],Models!A:C,3,FALSE) -> Mazda3 | J2: =VLOOKUP(Table2[[#This Row],[ModelID]],Models!A:C,2,FALSE) -> Mazda | K2: =VLOOKUP(Table2[[#This Row],[DealerID]], Dealers!A:D, 3,FALSE) -> Iloilo City | L2: =VLOOKUP(Table2[[#This Row],[DealerID]], Dealers!A:D, 2,FALSE) -> Iloilo Motors
A3: 2 | B3: 44569 | C3: =RANDBETWEEN(1,10) -> 1 | D3: =RANDBETWEEN(1,15) -> 12 | E3: 1 | F3: =Table2[[#This Row],[Quantity]]*(INDEX(Models!G:G,MATCH(Table2[[#This Row],[ModelID]],Models!A:A,0))) -> 34000 | G3: =Table2[[#This Row],[Quantity]]*(INDEX(Models!H:H,MATCH(Table2[[#This Row],[ModelID]],Models!A:A,0))) -> 3400 | H3: =VLOOKUP(Table2[[#This Row],[DealerID]], Dealers!A:D, 4,FALSE) -> Malaysia | I3: =VLOOKUP(Table2[[#This Row],[ModelID]],Models!A:C,3,FALSE) -> Santa Fe | J3: =VLOOKUP(Table2[[#This Row],[ModelID]],Models!A:C,2,FALSE) -> Hyundai | K3: =VLOOKUP(Table2[[#This Row],[DealerID]], Dealers!A:D, 3,FALSE) -> Kuala Lumpur | L3: =VLOOKUP(Table2[[#This Row],[DealerID]], Dealers!A:D, 2,FALSE) -> ABC Motors
A4: 3 | B4: 44604 | C4: =RANDBETWEEN(1,10) -> 1 | D4: =RANDBETWEEN(1,15) -> 8 | E4: 2 | F4: =Table2[[#This Row],[Quantity]]*(INDEX(Models!G:G,MATCH(Table2[[#This Row],[ModelID]],Models!A:A,0))) -> 52000 | G4: =Table2[[#This Row],[Quantity]]*(INDEX(Models!H:H,MATCH(Table2[[#This Row],[ModelID]],Models!A:A,0))) -> 5200 | H4: =VLOOKUP(Table2[[#This Row],[DealerID]], Dealers!A:D, 4,FALSE) -> Malaysia | I4: =VLOOKUP(Table2[[#This Row],[ModelID]],Models!A:C,3,FALSE) -> X-Trail | J4: =VLOOKUP(Table2[[#This Row],[ModelID]],Models!A:C,2,FALSE) -> Nissan | K4: =VLOOKUP(Table2[[#This Row],[DealerID]], Dealers!A:D, 3,FALSE) -> Kuala Lumpur | L4: =VLOOKUP(Table2[[#This Row],[DealerID]], Dealers!A:D, 2,FALSE) -> ABC Motors
A5: 4 | B5: 44614 | C5: =RANDBETWEEN(1,10) -> 6 | D5: =RANDBETWEEN(1,15) -> 6 | E5: 1 | F5: =Table2[[#This Row],[Quantity]]*(INDEX(Models!G:G,MATCH(Table2[[#This Row],[ModelID]],Models!A:A,0))) -> 30000 | G5: =Table2[[#This Row],[Quantity]]*(INDEX(Models!H:H,MATCH(Table2[[#This Row],[ModelID]],Models!A:A,0))) -> 3000 | H5: =VLOOKUP(Table2[[#This Row],[DealerID]], Dealers!A:D, 4,FALSE) -> Philippines | I5: =VLOOKUP(Table2[[#This Row],[ModelID]],Models!A:C,3,FALSE) -> Everest | J5: =VLOOKUP(Table2[[#This Row],[ModelID]],Models!A:C,2,FALSE) -> Ford | K5: =VLOOKUP(Table2[[#This Row],[DealerID]], Dealers!A:D, 3,FALSE) -> Davao City | L5: =VLOOKUP(Table2[[#This Row],[DealerID]], Dealers!A:D, 2,FALSE) -> Davao Dealers
A6: 5 | B6: 44621 | C6: =RANDBETWEEN(1,10) -> 9 | D6: =RANDBETWEEN(1,15) -> 3 | E6: 3 | F6: =Table2[[#This Row],[Quantity]]*(INDEX(Models!G:G,MATCH(Table2[[#This Row],[ModelID]],Models!A:A,0))) -> 66000 | G6: =Table2[[#This Row],[Quantity]]*(INDEX(Models!H:H,MATCH(Table2[[#This Row],[ModelID]],Models!A:A,0))) -> 13200 | H6: =VLOOKUP(Table2[[#This Row],[DealerID]], Dealers!A:D, 4,FALSE) -> Philippines | I6: =VLOOKUP(Table2[[#This Row],[ModelID]],Models!A:C,3,FALSE) -> Civic | J6: =VLOOKUP(Table2[[#This Row],[ModelID]],Models!A:C,2,FALSE) -> Honda | K6: =VLOOKUP(Table2[[#This Row],[DealerID]], Dealers!A:D, 3,FALSE) -> Iloilo City | L6: =VLOOKUP(Table2[[#This Row],[DealerID]], Dealers!A:D, 2,FALSE) -> Iloilo Motors
A7: 6 | B7: 44628 | C7: =RANDBETWEEN(1,10) -> 6 | D7: =RANDBETWEEN(1,15) -> 11 | E7: 1 | F7: =Table2[[#This Row],[Quantity]]*(INDEX(Models!G:G,MATCH(Table2[[#This Row],[ModelID]],Models!A:A,0))) -> 16000 | G7: =Table2[[#This Row],[Quantity]]*(INDEX(Models!H:H,MATCH(Table2[[#This Row],[ModelID]],Models!A:A,0))) -> 3200 | H7: =VLOOKUP(Table2[[#This Row],[DealerID]], Dealers!A:D, 4,FALSE) -> Philippines | I7: =VLOOKUP(Table2[[#This Row],[ModelID]],Models!A:C,3,FALSE) -> Accent | J7: =VLOOKUP(Table2[[#This Row],[ModelID]],Models!A:C,2,FALSE) -> Hyundai | K7: =VLOOKUP(Table2[[#This Row],[DealerID]], Dealers!A:D, 3,FALSE) -> Davao City | L7: =VLOOKUP(Table2[[#This Row],[DealerID]], Dealers!A:D, 2,FALSE) -> Davao Dealers
A8: 7 | B8: 44629 | C8: =RANDBETWEEN(1,10) -> 8 | D8: =RANDBETWEEN(1,15) -> 9 | E8: 2 | F8: =Table2[[#This Row],[Quantity]]*(INDEX(Models!G:G,MATCH(Table2[[#This Row],[ModelID]],Models!A:A,0))) -> 36000 | G8: =Table2[[#This Row],[Quantity]]*(INDEX(Models!H:H,MATCH(Table2[[#This Row],[ModelID]],Models!A:A,0))) -> 3600 | H8: =VLOOKUP(Table2[[#This Row],[DealerID]], Dealers!A:D, 4,FALSE) -> Philippines | I8: =VLOOKUP(Table2[[#This Row],[ModelID]],Models!A:C,3,FALSE) -> Xpander | J8: =VLOOKUP(Table2[[#This Row],[ModelID]],Models!A:C,2,FALSE) -> Mitsubishi | K8: =VLOOKUP(Table2[[#This Row],[DealerID]], Dealers!A:D, 3,FALSE) -> Bacolod City | L8: =VLOOKUP(Table2[[#This Row],[DealerID]], Dealers!A:D, 2,FALSE) -> Bacolod Autos
A9: 8 | B9: 44630 | C9: =RANDBETWEEN(1,10) -> 3 | D9: =RANDBETWEEN(1,15) -> 12 | E9: 1 | F9: =Table2[[#This Row],[Quantity]]*(INDEX(Models!G:G,MATCH(Table2[[#This Row],[ModelID]],Models!A:A,0))) -> 34000 | G9: =Table2[[#This Row],[Quantity]]*(INDEX(Models!H:H,MATCH(Table2[[#This Row],[ModelID]],Models!A:A,0))) -> 3400 | H9: =VLOOKUP(Table2[[#This Row],[DealerID]], Dealers!A:D, 4,FALSE) -> Singapore | I9: =VLOOKUP(Table2[[#This Row],[ModelID]],Models!A:C,3,FALSE) -> Santa Fe | J9: =VLOOKUP(Table2[[#This Row],[ModelID]],Models!A:C,2,FALSE) -> Hyundai | K9: =VLOOKUP(Table2[[#This Row],[DealerID]], Dealers!A:D, 3,FALSE) -> Singapore | L9: =VLOOKUP(Table2[[#This Row],[DealerID]], Dealers!A:D, 2,FALSE) -> Singapore Autos
A10: 9 | B10: 44631 | C10: =RANDBETWEEN(1,10) -> 10 | D10: =RANDBETWEEN(1,15) -> 4 | E10: 1 | F10: =Table2[[#This Row],[Quantity]]*(INDEX(Models!G:G,MATCH(Table2[[#This Row],[ModelID]],Models!A:A,0))) -> 28000 | G10: =Table2[[#This Row],[Quantity]]*(INDEX(Models!H:H,MATCH(Table2[[#This Row],[ModelID]],Models!A:A,0))) -> 2800 | H10: =VLOOKUP(Table2[[#This Row],[DealerID]], Dealers!A:D, 4,FALSE) -> Philippines | I10: =VLOOKUP(Table2[[#This Row],[ModelID]],Models!A:C,3,FALSE) -> CR-V | J10: =VLOOKUP(Table2[[#This Row],[ModelID]],Models!A:C,2,FALSE) -> Honda | K10: =VLOOKUP(Table2[[#This Row],[DealerID]], Dealers!A:D, 3,FALSE) -> Zamboanga City | L10: =VLOOKUP(Table2[[#This Row],[DealerID]], Dealers!A:D, 2,FALSE) -> Zamboanga Cars
A11: 10 | B11: 44632 | C11: =RANDBETWEEN(1,10) -> 9 | D11: =RANDBETWEEN(1,15) -> 3 | E11: 2 | F11: =Table2[[#This Row],[Quantity]]*(INDEX(Models!G:G,MATCH(Table2[[#This Row],[ModelID]],Models!A:A,0))) -> 44000 | G11: =Table2[[#This Row],[Quantity]]*(INDEX(Models!H:H,MATCH(Table2[[#This Row],[ModelID]],Models!A:A,0))) -> 8800 | H11: =VLOOKUP(Table2[[#This Row],[DealerID]], Dealers!A:D, 4,FALSE) -> Philippines | I11: =VLOOKUP(Table2[[#This Row],[ModelID]],Models!A:C,3,FALSE) -> Civic | J11: =VLOOKUP(Table2[[#This Row],[ModelID]],Models!A:C,2,FALSE) -> Honda | K11: =VLOOKUP(Table2[[#This Row],[DealerID]], Dealers!A:D, 3,FALSE) -> Iloilo City | L11: =VLOOKUP(Table2[[#This Row],[DealerID]], Dealers!A:D, 2,FALSE) -> Iloilo Motors
A12: 11 | B12: 44635 | C12: =RANDBETWEEN(1,10) -> 10 | D12: =RANDBETWEEN(1,15) -> 2 | E12: 1 | F12: =Table2[[#This Row],[Quantity]]*(INDEX(Models!G:G,MATCH(Table2[[#This Row],[ModelID]],Models!A:A,0))) -> 20000 | G12: =Table2[[#This Row],[Quantity]]*(INDEX(Models!H:H,MATCH(Table2[[#This Row],[ModelID]],Models!A:A,0))) -> 2000 | H12: =VLOOKUP(Table2[[#This Row],[DealerID]], Dealers!A:D, 4,FALSE) -> Philippines | I12: =VLOOKUP(Table2[[#This Row],[ModelID]],Models!A:C,3,FALSE) -> Corolla Altis | J12: =VLOOKUP(Table2[[#This Row],[ModelID]],Models!A:C,2,FALSE) -> Toyota | K12: =VLOOKUP(Table2[[#This Row],[DealerID]], Dealers!A:D, 3,FALSE) -> Zamboanga City | L12: =VLOOKUP(Table2[[#This Row],[DealerID]], Dealers!A:D, 2,FALSE) -> Zamboanga Cars
A13: 12 | B13: 44636 | C13: =RANDBETWEEN(1,10) -> 6 | D13: =RANDBETWEEN(1,15) -> 15 | E13: 1 | F13: =Table2[[#This Row],[Quantity]]*(INDEX(Models!G:G,MATCH(Table2[[#This Row],[ModelID]],Models!A:A,0))) -> 24000 | G13: =Table2[[#This Row],[Quantity]]*(INDEX(Models!H:H,MATCH(Table2[[#This Row],[ModelID]],Models!A:A,0))) -> 2400 | H13: =VLOOKUP(Table2[[#This Row],[DealerID]], Dealers!A:D, 4,FALSE) -> Philippines | I13: =VLOOKUP(Table2[[#This Row],[ModelID]],Models!A:C,3,FALSE) -> Mazda3 | J13: =VLOOKUP(Table2[[#This Row],[ModelID]],Models!A:C,2,FALSE) -> Mazda | K13: =VLOOKUP(Table2[[#This Row],[DealerID]], Dealers!A:D, 3,FALSE) -> Davao City | L13: =VLOOKUP(Table2[[#This Row],[DealerID]], Dealers!A:D, 2,FALSE) -> Davao Dealers
... A219: 218 | B219: 44924 | C219: =RANDBETWEEN(1,10) -> 3 | D219: =RANDBETWEEN(1,15) -> 7 | E219: 3 | F219: =Table2[[#This Row],[Quantity]]*(INDEX(Models!G:G,MATCH(Table2[[#This Row],[ModelID]],Models!A:A,0))) -> 42000 | G219: =Table2[[#This Row],[Quantity]]*(INDEX(Models!H:H,MATCH(Table2[[#This Row],[ModelID]],Models!A:A,0))) -> 4200 | H219: =VLOOKUP(Table2[[#This Row],[DealerID]], Dealers!A:D, 4,FALSE) -> Singapore | I219: =VLOOKUP(Table2[[#This Row],[ModelID]],Models!A:C,3,FALSE) -> Almera | J219: =VLOOKUP(Table2[[#This Row],[ModelID]],Models!A:C,2,FALSE) -> Nissan | K219: =VLOOKUP(Table2[[#This Row],[DealerID]], Dealers!A:D, 3,FALSE) -> Singapore | L219: =VLOOKUP(Table2[[#This Row],[DealerID]], Dealers!A:D, 2,FALSE) -> Singapore Autos

Sheet Number1
A3: Row Labels | B3: Sum of Total Profit
A4: Malaysia | B4: 178300
A5: Philippines | B5: 717300
A6: Singapore | B6: 58100
A7: Grand Total | B7: 953700
D19: 1. Present Revenue by Country
D21: From the table given above it displays the revenue of each country. We can see that the highest revenue is from the Country Philippines, Second is Malaysia, and the least revenue in terms of Country is Singapore. Another information to take is one reason why Phillippines have the highest revenue is because in the data there a lot of dealers that are located in the Country for example is the Davao dealers, Cebu Cars, and manila motors.

Sheet Number 2
A3: Row Labels | B3: Sum of Quantity | K3: Row Labels | L3: Sum of Quantity
A4: Santa Fe | B4: 40 | K4: Hyundai | L4: 52
A5: Vios | B5: 30 | K5: Mitsubishi | L5: 63
A6: X-Trail | B6: 37 | K6: Nissan | L6: 49
A7: Grand Total | B7: 107 | K7: Grand Total | L7: 164
B14: 2. Identify the Top 3 Cars Sold
B16: From the given graph and table above the top 3 Cars(base on models) are; First is Santa Fe with 40 Cars Sold, Second is X-Trial with 37 cars sold, and Lastly is Vios with 30 cars sold | N16: This table provides the information of the top 3 car brands sold. With the highest sold is mitsubishi with 63 units, second is Hyundai with 52 units, and lastly is nissan with 49 units.

Sheet Number 3
A3: Row Labels | B3: Sum of Quantity | C3: Sum of Total Profit
A4: Ford | B4: 38 | C4: 106500
A5: Honda | B5: 42 | C5: 151200
A6: Hyundai | B6: 52 | C6: 169800
A7: Mazda | B7: 31 | C7: 74400
A8: Mitsubishi | B8: 63 | C8: 145600
A9: Nissan | B9: 49 | C9: 98600
A10: Proton | B10: 30 | C10: 119600
A11: Toyota | B11: 42 | C11: 71500
A12: Grand Total | B12: 347 | C12: 937200
B19: 3. Profit vs Sale Quantity between brands
B21: Base from the graph we can see that highest quantity sold is the Mitsubishi brand with a quantity of 63 units sold, but only in the 3rd place in terms of its total Profits with the numbers of 145,600 unlike the other two shich is Honda with a 42 units sold but has the second highest total profit with 151200 and the Hyundai with only 52 units sold but with a 169,800 of profits. | H21: Another 2 brands that are worth comparing is also the nissan and Proton Brands because of how close they are in terms of units sold but differs from each others total profits where Proton has 119600 total profits while the nissan only has 98600

Sheet Number 4
A1: Row Labels | B1: Sum of Total Profit | C1: Sum of TotalPrice
A2: Bacolod City | B2: 115600 | C2: 915000
A3: Bacolod Autos | B3: 115600 | C3: 915000
A4: Cebu City | B4: 120200 | C4: 944000 | U4: 4. Visualize Revenue and sales by City and Dealer
A5: Cebu Cars | B5: 120200 | C5: 944000
A6: Davao City | B6: 67800 | C6: 678000
A7: Davao Dealers | B7: 67800 | C7: 678000 | U7: From the data provided and the graph from the left we can analyze the top 3 in terms of location depending of its revenue. First is at Ilo ilo City with a 166900 in revenue. Cebu City comes second with a 120200 in revenue and lastly Bacolod City which comes close to Cebu City with a 115600 in revenue
A8: George Town | B8: 81000 | C8: 696000
A9: XYZ Cars | B9: 81000 | C9: 696000
A10: Iloilo City | B10: 166900 | C10: 1323000
A11: Iloilo Motors | B11: 166900 | C11: 1323000
A12: Kuala Lumpur | B12: 85900 | C12: 745000
A13: ABC Motors | B13: 85900 | C13: 745000
A14: Manila | B14: 64500 | C14: 468000
A15: Manila Motors | B15: 64500 | C15: 468000
A16: Quezon City | B16: 75600 | C16: 575000
A17: Quezon Vehicles | B17: 75600 | C17: 575000
A18: Singapore | B18: 64200 | C18: 576000
A19: Singapore Autos | B19: 64200 | C19: 576000
... A22: Grand Total | B22: 937200 | C22: 7800000
